yari_py_macos_arm-0.2.1.dist-info/METADATA
yari_py_macos_arm-0.2.1.dist-info/WHEEL
yari/__init__.py
yari/yari.cpython-312-darwin.so
yari_py_macos_arm-0.2.1.dist-info/RECORD
